{"entities": [{"name": "Brooklyn Entity Mirror", "type": "org.apache.brooklyn.entity.brooklynnode.BrooklynEntityMirror", "iconUrl": "", "effectors": [], "sensors": [{"type": "java.lang.String", "name": "brooklyn.mirror.catalog_item_id", "links": {}, "description": "The catalog item id of the mirrored entity in the remote brooklyn"}, {"type": "java.lang.String", "name": "brooklyn.mirror.monitoring_status", "links": {}, "description": "brooklyn.mirror.monitoring_status"}, {"type": "java.util.Map", "name": "brooklyn.mirror.summary", "links": {}, "description": "The json map returned by the entity rest endpoint (ie the EntitySummary model)"}], "config": [{"type": "java.lang.String", "name": "brooklyn.mirror.entity_id", "reconfigurable": false, "description": "Brooklyn ID of the entity being mirrored"}, {"type": "java.lang.String", "name": "brooklyn.mirror.entity_url", "reconfigurable": false, "description": "URL for the entity in the remote Brooklyn mgmt endpoint"}, {"defaultValue": "5s", "type": "org.apache.brooklyn.util.time.Duration", "name": "brooklyn.mirror.poll_period", "reconfigurable": false, "description": "Frequency to poll for client sensors"}, {"type": "java.lang.String", "name": "brooklynnode.managementPassword", "reconfigurable": false, "description": "Password for MANAGEMENT_USER"}, {"defaultValue": "admin", "type": "java.lang.String", "name": "brooklynnode.managementUser", "reconfigurable": false, "description": "The user for logging into the brooklyn web-console (also used for health-checks)"}], "description": "Provides an entity which can sit in one brooklyn domain and reflect the status of an entity via the REST API of another domain."}]}